calculator_package/calculator.py
calculator_package_zversal-0.1.0.dist-info/METADATA
calculator_package_zversal-0.1.0.dist-info/WHEEL
calculator_package_zversal-0.1.0.dist-info/top_level.txt
calculator_package_zversal-0.1.0.dist-info/RECORD
