Metadata-Version: 2.2
Name: calculator_package.zversal
Version: 0.1.0
Summary: A package to process PDFs using fitz (PyMuPDF)
Author-email: Nikkhil <nikkhil.zversal@gmail.com>
License: MIT
Requires-Python: >=3.12
Requires-Dist: pymupdf
